Workbook

Sheet Dashboard
B2: Business Sales Performance Analysis & Decision Dashboard
B3: Maincrafts Technology | Prepared by: Business Analytics Intern | Data period: Jan–Dec 2024
B5: Total Revenue | E5: Total Profit | H5: Avg Profit Margin | K5: Total Orders
B7: =SUM(Cleaned_Data!$I$2:$I$315) -> 6848966.7 | E7: =SUM(Cleaned_Data!$G$2:$G$315) -> 1142001.6 | H7: =SUM(Cleaned_Data!$G$2:$G$315)/SUM(Cleaned_Data!$I$2:$I$315) -> 0.16674072 | K7: =COUNTA(Cleaned_Data!$H$2:$H$315) -> 314
B11: Best Performing Region: | D11: =INDEX(Sales_by_Region!A2:A6,MATCH(MAX(Sales_by_Region!B2:B6),Sales_by_Region!B2:B6,0)) -> North
B12: Top Product: | D12: =INDEX(Sales_by_Product!A2:A17,MATCH(MAX(Sales_by_Product!B2:B17),Sales_by_Product!B2:B17,0)) -> Office Chair

Sheet Raw_Data
A1: Order_ID | B1: Order_Date | C1: Region | D1: Product | E1: Category | F1: Sales_Amount | G1: Profit | H1: Quantity
A2: 1014 | B2: 2024-07-04 | C2: West | D2: Whiteboard | E2: Stationery | F2: 598.53 | G2: 545.06 | H2: 4
A3: 1158 | B3: 2024-09-09 | C3: East | D3: Wireless Mouse | E3: Electronics | F3: 1159.61 | G3: 607.55 | H3: 2
A4: 1007 | B4: 2024-12-26 | C4: South | D4: Sticky Notes | E4: Stationery | F4: 75.2 | G4: 36.94 | H4: 2
A5: 1250 | B5: 2024-12-30 | C5: South | D5: Sticky Notes | E5: Stationery | F5: 560.03 | G5: 2201.19 | H5: 12
A6: 1064 | B6: 2024-12-06 | C6: West | D6: Standing Desk | E6: Furniture | F6: 8934.52 | G6: 11778.88 | H6: 7
A7: 1046 | B7: 2024-05-15 | C7: South | D7: Notebook Pack | E7: Stationery | F7: 539.34 | G7: 375.9 | H7: 2
A8: 1204 | B8: 2024-02-01 | C8: South | D8: Electric Kettle | E8: Appliances | F8: 1645.06 | G8: 2736 | H8: 8
A9: 1186 | B9: 2024-12-11 | C9: North | D9: Standing Desk | E9: Furniture | F9: 5084.98 | G9: 1621.42 | H9: 2
A10: 1269 | B10: 2024-05-24 | C10: North | D10: Notebook Pack | E10: Stationery | F10: 378.64 | G10: 1116.44 | H10: 8
A11: 1283 | B11: 2024-12-27 | C11: North | D11: Electric Kettle | E11: Appliances | F11: 3430.34 | G11: 1721.75 | H11: 3
A12: 1069 | B12: 2024-08-21 | C12: North | D12: Electric Kettle | E12: Appliances | F12: 5010.39 | G12: 5930.12 | H12: 7
A13: 1015 | B13: 2024-02-26 | C13: North | D13: Coffee Maker | E13: Appliances | F13: 3898.02 | G13: 2280.92 | H13: 3
... A122: 1107 | B122: 2024-10-12 | C122: North | D122: Bluetooth Speaker | E122: Electronics | F122: 3043.38 | G122: 5251.75 | H122: 7
A123: 1257 | B123: 2024-02-10 | D123: Bookshelf | E123: Furniture | F123: 4364.87 | G123: 4250.56 | H123: 5
A124: 1102 | B124: 2024-02-21 | C124: East | D124: Desk Fan | E124: Appliances | F124: 2473.86 | G124: 1418.07 | H124: 4
A125: 1170 | B125: 2024-08-19 | C125: North | D125: Desk Fan | E125: Appliances | F125: 2152.66 | G125: 3367.44 | H125: 9
A126: 1020 | B126: 2024-03-23 | C126: East | D126: Standing Desk | E126: Furniture | F126: 11558.25 | G126: 19836.6 | H126: 9
A127: 1179 | B127: 2024-01-27 | C127: West | D127: Desk Fan | E127: Appliances | F127: 3781.76 | G127: 2688.78 | H127: 5
A128: 1118 | B128: 2024-03-30 | C128: North | D128: USB-C Hub | E128: Electronics | F128: 2720.17 | G128: 4151.13 | H128: 8
A129: 1306 | B129: 2024-05-06 | C129: South | D129: Electric Kettle | E129: Appliances | F129: 4445.38 | G129: 10013.39 | H129: 11
A130: 1049 | B130: 2024-03-07 | C130: East | D130: Wireless Mouse | E130: Electronics | F130: 4425.25 | G130: 7099.8 | H130: 11
A131: 1291 | B131: 2024-02-21 | C131: North | D131: Standing Desk | E131: Furniture | F131: 5637.79 | G131: 5394.35 | H131: 7
A132: 1207 | B132: 2024-06-17 | C132: North | D132: USB-C Hub | E132: Electronics | F132: 2864.46 | G132: 1041.81 | H132: 2
A133: 1246 | B133: 2024-04-05 | C133: North | D133: Office Chair | E133: Furniture | F133: 7418.58 | G133: 11253.99 | H133: 8
A134: 1117 | B134: 2024-02-16 | C134: North | D134: Sticky Notes | E134: Stationery | F134: 579.05 | G134: 850.49 | H134: 4
A135: 1288 | B135: 2024-05-28 | C135: South | D135: Desk Fan | E135: Appliances | F135: 2436.81 | G135: 452.51 | H135: 1
A136: 1178 | B136: 2024-10-27 | C136: North | D136: Pen Set | E136: Stationery | F136: 358.93 | G136: 1078.95 | H136: 9
A137: 1316 | B137: 2024-06-01 | C137: North | D137: Office Chair | E137: Furniture | F137: 8898.25 | G137: 10345.71
A138: 1009 | B138: 2024-06-30 | C138: East | D138: Pen Set | E138: Stationery | F138: 418.6 | G138: 569.91 | H138: 4
A139: 1112 | B139: 2024-05-15 | C139: South | D139: Coffee Maker | E139: Appliances | F139: 3736.1 | G139: 8074.29 | H139: 11
A140: 1240 | B140: 2024-03-26 | C140: West | D140: Electric Kettle | E140: Appliances | F140: 3108.81 | G140: 5732.23 | H140: 12
A141: 1111 | B141: 2024-04-28 | C141: North | D141: Desk Fan | E141: Appliances | F141: 4239.91 | G141: 3908.32 | H141: 5
A142: 1119 | B142: 2024-11-21 | C142: West | D142: Pen Set | E142: Stationery | F142: 582.98 | G142: 1371.18 | H142: 8
A143: 1308 | B143: 2024-10-20 | C143: South | D143: Wireless Mouse | E143: Electronics | F143: 1354.45 | G143: 2102.77 | H143: 9
A144: 1167 | B144: 2024-10-03 | C144: South | D144: Pen Set | E144: Stationery | F144: 489.18 | G144: 542.95 | H144: 5
A145: 1024 | B145: 2024-10-03 | C145: South | D145: Whiteboard | E145: Stationery | F145: 429.43 | G145: 1765.42 | H145: 12
A146: 1176 | B146: 2024-06-09 | C146: North | D146: Electric Kettle | E146: Appliances | F146: 2543.85 | G146: 2325.35 | H146: 7
A147: 1254 | B147: 2024-11-24 | C147: East | D147: Bluetooth Speaker | E147: Electronics | F147: 2464.91 | G147: 1128.03 | H147: 2
A148: 1091 | B148: 2024-01-07 | C148: East | D148: Notebook Pack | E148: Stationery | F148: 502.28 | G148: 777.41 | H148: 7
A149: 1077 | B149: 2024-07-31 | C149: North | D149: Standing Desk | E149: Furniture | F149: 5643.37 | G149: 5368.97 | H149: 7
... A153: 1209 | B153: 2024-10-31 | C153: South | D153: Whiteboard | E153: Stationery | F153: 565.9 | G153: 1778.62 | H153: 12
A154: 1320 | B154: 2024-09-14 | C154: South | D154: Office Chair | E154: Furniture | F154: 4724.53 | H154: 5
A155: 1082 | B155: 2024-02-12 | C155: North | D155: Laptop Stand | E155: Electronics | F155: 2385.87 | G155: 6789.37 | H155: 11
A156: 1058 | B156: 2024-11-24 | C156: East | D156: USB-C Hub | E156: Electronics | F156: 2278.81 | G156: 5680.74 | H156: 9
A157: 1122 | B157: 2024-09-20 | C157: West | D157: Notebook Pack | E157: Stationery | F157: 411.71 | G157: 127.02 | H157: 1
A158: 1027 | B158: 2024-02-04 | C158: South | D158: Wireless Mouse | E158: Electronics | F158: 3980.65 | G158: 522.81 | H158: 1
A159: 1141 | B159: 2024-05-05 | C159: South | D159: Whiteboard | E159: Stationery | F159: 276.63 | G159: 837.43 | H159: 9
A160: 1304 | B160: 2024-07-07 | C160: East | D160: Notebook Pack | E160: Stationery | F160: 171.47 | G160: 671.26 | H160: 10
A161: 1243 | B161: 2024-11-26 | C161: South | D161: Office Chair | E161: Furniture | F161: 5940.43 | G161: 6912.38 | H161: 6
A162: 1248 | B162: 2024-03-10 | C162: North | D162: Coffee Maker | E162: Appliances | F162: 3143.78 | G162: 1306.82 | H162: 2
A163: 1211 | B163: 2024-01-10 | C163: East | D163: Laptop Stand | E163: Electronics | F163: 1942.8 | G163: 3172.83 | H163: 6
A164: 1078 | B164: 2024-07-18 | C164: West | D164: Bluetooth Speaker | E164: Electronics | F164: 4300.43 | G164: 5294.91 | H164: 10
A165: 1273 | B165: 2024-07-20 | C165: North | D165: Bluetooth Speaker | E165: Electronics | F165: 3741.12 | G165: 3911.42 | H165: 6
A166: 1222 | B166: 30/04/2024 | C166: East | D166: Electric Kettle | E166: Appliances | F166: 5476.46 | G166: 5558.21 | H166: 7
... A201: 1180 | B201: 2024-04-24 | C201: West | D201: Standing Desk | E201: Furniture | F201: 5826.08 | G201: 1709.98 | H201: 2
A202: 1008 | B202: 2024-02-21 | D202: Notebook Pack | E202: Stationery | F202: 202.89 | G202: 464.61 | H202: 7
A203: 1149 | B203: 2024-11-17 | C203: South | D203: Bookshelf | E203: Furniture | F203: 11082.34 | G203: 3492.29 | H203: 2
A204: 1075 | B204: 2024-05-20 | C204: South | D204: Electric Kettle | E204: Appliances | F204: 1533.18 | G204: 1647.09 | H204: 8
A205: 1224 | B205: 2024-12-22 | C205: West | D205: USB-C Hub | E205: Electronics | F205: 3607.71 | G205: 2111.13 | H205: 3
A206: 1231 | B206: 2024-06-25 | C206: North | D206: USB-C Hub | E206: Electronics | F206: 3511.88 | G206: 3097.77 | H206: 4
A207: 1249 | B207: 2024-12-07 | C207: East | D207: Coffee Maker | E207: Appliances | F207: 4251.02 | G207: 4234.01 | H207: 6
A208: 1066 | B208: 2024-08-14 | C208: West | D208: Whiteboard | E208: Stationery | G208: 543 | H208: 11
A209: 1261 | B209: 2024-11-24 | C209: East | D209: Laptop Stand | E209: Electronics | F209: 2586.9 | G209: 3217.46 | H209: 5
A210: 1036 | B210: 2024-12-22 | C210: West | D210: Desk Fan | E210: Appliances | F210: 5480.32 | G210: 10962.32 | H210: 12
A211: 1160 | B211: 2024-07-31 | C211: South | D211: Electric Kettle | E211: Appliances | F211: 1625.79 | G211: 2838.53 | H211: 11
A212: 1300 | B212: 2024-09-20 | C212: West | D212: Filing Cabinet | E212: Furniture | F212: 3324.01 | G212: 3197.25 | H212: 6
A213: 1121 | B213: 2024-10-08 | C213: West | D213: Desk Fan | E213: Appliances | F213: 3155.75 | G213: 434.68 | H213: 1
A214: 1171 | B214: 2024-02-01 | C214: North | D214: Whiteboard | E214: Stationery | F214: 516.01 | G214: 1177.55 | H214: 8
A215: 1303 | B215: 2024-12-07 | C215: North | D215: Pen Set | E215: Stationery | F215: 305.97 | G215: 141.94 | H215: 2
A216: 1234 | B216: 2024-04-13 | C216: East | D216: Coffee Maker | E216: Appliances | F216: 4601.77 | G216: 949.32 | H216: 1
A217: 1193 | B217: 2024-12-29 | C217: West | D217: Whiteboard | E217: Stationery | F217: 279.73 | G217: 686.28 | H217: 11
A218: 1286 | B218: 2024-12-19 | C218: South | D218: Sticky Notes | E218: Stationery | F218: 318.95 | G218: 1132.76 | H218: 12
A219: 1311 | B219: 12/01/2024 | C219: East | D219: Electric Kettle | E219: Appliances | G219: 1611.73 | H219: 7
A220: 1268 | B220: 2024-07-20 | C220: North | D220: Coffee Maker | E220: Appliances | F220: 3166.09 | G220: 3672.62 | H220: 9
A221: 1080 | B221: 2024-09-06 | C221: South | D221: Electric Kettle | E221: Appliances | F221: 2373.62 | G221: 1502.76 | H221: 4
A222: 1192 | B222: 2024-01-22 | C222: West | D222: Notebook Pack | E222: Stationery | F222: 60.31 | G222: 162.21 | H222: 7
A223: 1136 | B223: 2024-05-15 | C223: West | D223: Office Chair | E223: Furniture | F223: 8420.96 | G223: 6452.04 | H223: 6
A224: 1313 | B224: 2024-01-17 | C224: West | D224: Wireless Mouse | E224: Electronics | F224: 2312.81 | G224: 2810.48 | H224: 5
A225: 1120 | B225: 2024-12-09 | C225: East | D225: Desk Fan | E225: Appliances | F225: 4888.25 | G225: 1364.57 | H225: 2
A226: 1105 | B226: 2024-05-09 | C226: North | D226: Pen Set | E226: Stationery | F226: 112.75 | G226: 192.19 | H226: 8
A227: 1139 | B227: 2024-02-20 | C227: West | D227: Office Chair | E227: Furniture | F227: 9186.96 | G227: 9303.35 | H227: 11
A228: 1310 | B228: 2024-09-19 | C228: South | D228: Laptop Stand | E228: Electronics | F228: 2490.15 | G228: 2252.75 | H228: 7
A229: 1142 | B229: 2024-02-10 | C229: South | D229: Standing Desk | E229: Furniture | F229: 10772.98 | G229: 16629.74 | H229: 10
A230: 1016 | B230: 2024-07-16 | C230: North | D230: Electric Kettle | E230: Appliances | F230: 3762.32 | G230: 4112.82 | H230: 7
A231: 1128 | B231: 2024-05-04 | C231: West | D231: Desk Fan | E231: Appliances | F231: 3570.44 | H231: 8
A232: 1087 | B232: 2024-08-26 | C232: South | D232: Webcam HD | E232: Electronics | F232: 1748.1 | G232: 3755.41 | H232: 12
A233: 1172 | B233: 2024-02-07 | C233: West | D233: Laptop Stand | E233: Electronics | F233: 1991.81 | G233: 572.58 | H233: 2
A234: 1061 | B234: 2024-05-10 | C234: South | D234: Laptop Stand | E234: Electronics | F234: 3422.51 | G234: 411.63 | H234: 1
A235: 1098 | B235: 2024-08-17 | C235: West | D235: Electric Kettle | E235: Appliances | F235: 1600.13 | G235: 202.56 | H235: 1
A236: 1028 | B236: 2024-04-19 | C236: West | D236: Bookshelf | E236: Furniture | F236: 3756.96 | G236: 6500.88 | H236: 9
A237: 1018 | B237: 2024-08-10 | C237: East | D237: Notebook Pack | E237: Stationery | F237: 299.55 | G237: 351.16 | H237: 3
A238: 1235 | B238: 2024-10-05 | C238: West | D238: Sticky Notes | E238: Stationery | F238: 189.32 | G238: 531.09 | H238: 8
A239: 1237 | B239: 2024-08-13 | C239: West | D239: Whiteboard | E239: Stationery | F239: 236.47 | G239: 392.91 | H239: 7
A240: 1151 | B240: 2024-03-30 | C240: West | D240: Sticky Notes | E240: Stationery | F240: 122.69 | G240: 151.1 | H240: 4
A241: 1271 | B241: 2024-01-24 | C241: East | D241: Whiteboard | E241: Stationery | F241: 78.14 | G241: 170.86 | H241: 7
A242: 1236 | B242: 2024-01-25 | C242: East | D242: Bookshelf | E242: Furniture | F242: 5653.28 | G242: 5903.76 | H242: 11
A243: 1068 | B243: 2024-04-11 | C243: South | D243: Bookshelf | E243: Furniture | F243: 2732.04 | G243: 896.5 | H243: 3
... A278: 1278 | B278: 2024-08-01 | C278: North | D278: Sticky Notes | E278: Stationery | F278: 219.22 | G278: 832.5 | H278: 10
A279: 1191 | B279: 2024-07-13 | C279: South | D279: Coffee Maker | E279: Appliances | F279: 4225.79 | G279: 6086.33
...

Sheet Cleaned_Data
A1: Order_ID | B1: Order_Date | C1: Region | D1: Product | E1: Category | F1: Sales_Amount | G1: Profit | H1: Quantity | I1: Total_Sales | J1: Profit_Margin
A2: 1035 | B2: 45293 | C2: West | D2: Bluetooth Speaker | E2: Electronics | F2: 1781.25 | G2: 3060.47 | H2: 7 | I2: =F2*H2 -> 12468.75 | J2: =IF(I2=0,0,G2/I2) -> 0.24545123
A3: 1104 | B3: 45298 | C3: North | D3: Filing Cabinet | E3: Furniture | F3: 5201.22 | G3: 7148.85 | H3: 10 | I3: =F3*H3 -> 52012.2 | J3: =IF(I3=0,0,G3/I3) -> 0.13744564
A4: 1091 | B4: 45298 | C4: East | D4: Notebook Pack | E4: Stationery | F4: 502.28 | G4: 777.41 | H4: 7 | I4: =F4*H4 -> 3515.96 | J4: =IF(I4=0,0,G4/I4) -> 0.22110889
A5: 1211 | B5: 45301 | C5: East | D5: Laptop Stand | E5: Electronics | F5: 1942.8 | G5: 3172.83 | H5: 6 | I5: =F5*H5 -> 11656.8 | J5: =IF(I5=0,0,G5/I5) -> 0.27218705
A6: 1086 | B6: 45302 | C6: South | D6: Bluetooth Speaker | E6: Electronics | F6: 1363.81 | G6: 1912 | H6: 10 | I6: =F6*H6 -> 13638.1 | J6: =IF(I6=0,0,G6/I6) -> 0.14019548
A7: 1156 | B7: 45304 | C7: West | D7: Bluetooth Speaker | E7: Electronics | F7: 4071.67 | G7: 8543.39 | H7: 10 | I7: =F7*H7 -> 40716.7 | J7: =IF(I7=0,0,G7/I7) -> 0.20982521
A8: 1182 | B8: 45306 | C8: East | D8: Webcam HD | E8: Electronics | F8: 1811.1 | G8: 1314.78 | H8: 3 | I8: =F8*H8 -> 5433.3 | J8: =IF(I8=0,0,G8/I8) -> 0.24198553
A9: 1313 | B9: 45308 | C9: West | D9: Wireless Mouse | E9: Electronics | F9: 2312.81 | G9: 2810.48 | H9: 5 | I9: =F9*H9 -> 11564.05 | J9: =IF(I9=0,0,G9/I9) -> 0.24303596
A10: 1281 | B10: 45308 | C10: South | D10: Coffee Maker | E10: Appliances | F10: 5277.28 | G10: 5973.22 | H10: 10 | I10: =F10*H10 -> 52772.8 | J10: =IF(I10=0,0,G10/I10) -> 0.11318748
A11: 1002 | B11: 45308 | C11: West | D11: Webcam HD | E11: Electronics | F11: 1146.67 | G11: 180.29 | H11: 1 | I11: =F11*H11 -> 1146.67 | J11: =IF(I11=0,0,G11/I11) -> 0.15722919
A12: 1295 | B12: 45310 | C12: South | D12: Filing Cabinet | E12: Furniture | F12: 9985.63 | G12: 7154.72 | H12: 7 | I12: =F12*H12 -> 69899.41 | J12: =IF(I12=0,0,G12/I12) -> 0.10235737
A13: 1205 | B13: 45312 | C13: South | D13: Notebook Pack | E13: Stationery | F13: 439.19 | G13: 699.54 | H13: 4 | I13: =F13*H13 -> 1756.76 | J13: =IF(I13=0,0,G13/I13) -> 0.39819896
... A315: 1223 | B315: 45657 | C315: North | D315: USB-C Hub | E315: Electronics | F315: 2040.57 | G315: 3218.07 | H315: 11 | I315: =F315*H315 -> 22446.27 | J315: =IF(I315=0,0,G315/I315) -> 0.1433677

Sheet Sales_by_Region
A1: Region | B1: Total Sales | C1: Total Profit | D1: Order Count
A2: East | B2: =SUMIF(Cleaned_Data!$C$2:$C$315,A2,Cleaned_Data!$I$2:$I$315) -> 1772409.1 | C2: =SUMIF(Cleaned_Data!$C$2:$C$315,A2,Cleaned_Data!$G$2:$G$315) -> 283781.87 | D2: =COUNTIF(Cleaned_Data!$C$2:$C$315,A2) -> 69
A3: North | B3: =SUMIF(Cleaned_Data!$C$2:$C$315,A3,Cleaned_Data!$I$2:$I$315) -> 1813985 | C3: =SUMIF(Cleaned_Data!$C$2:$C$315,A3,Cleaned_Data!$G$2:$G$315) -> 297072.02 | D3: =COUNTIF(Cleaned_Data!$C$2:$C$315,A3) -> 88
A4: South | B4: =SUMIF(Cleaned_Data!$C$2:$C$315,A4,Cleaned_Data!$I$2:$I$315) -> 1608310.8 | C4: =SUMIF(Cleaned_Data!$C$2:$C$315,A4,Cleaned_Data!$G$2:$G$315) -> 277412.26 | D4: =COUNTIF(Cleaned_Data!$C$2:$C$315,A4) -> 77
A5: Unspecified | B5: =SUMIF(Cleaned_Data!$C$2:$C$315,A5,Cleaned_Data!$I$2:$I$315) -> 23244.58 | C5: =SUMIF(Cleaned_Data!$C$2:$C$315,A5,Cleaned_Data!$G$2:$G$315) -> 4715.17 | D5: =COUNTIF(Cleaned_Data!$C$2:$C$315,A5) -> 2
A6: West | B6: =SUMIF(Cleaned_Data!$C$2:$C$315,A6,Cleaned_Data!$I$2:$I$315) -> 1631017.1 | C6: =SUMIF(Cleaned_Data!$C$2:$C$315,A6,Cleaned_Data!$G$2:$G$315) -> 279020.33 | D6: =COUNTIF(Cleaned_Data!$C$2:$C$315,A6) -> 78

Sheet Sales_by_Product
A1: Product | B1: Total Sales | C1: Units Sold
A2: Office Chair | B2: =SUMIF(Cleaned_Data!$D$2:$D$315,A2,Cleaned_Data!$I$2:$I$315) -> 1023261 | C2: =SUMIF(Cleaned_Data!$D$2:$D$315,A2,Cleaned_Data!$H$2:$H$315) -> 125
A3: Bookshelf | B3: =SUMIF(Cleaned_Data!$D$2:$D$315,A3,Cleaned_Data!$I$2:$I$315) -> 921004.07 | C3: =SUMIF(Cleaned_Data!$D$2:$D$315,A3,Cleaned_Data!$H$2:$H$315) -> 127
A4: Filing Cabinet | B4: =SUMIF(Cleaned_Data!$D$2:$D$315,A4,Cleaned_Data!$I$2:$I$315) -> 841772.92 | C4: =SUMIF(Cleaned_Data!$D$2:$D$315,A4,Cleaned_Data!$H$2:$H$315) -> 106
A5: Coffee Maker | B5: =SUMIF(Cleaned_Data!$D$2:$D$315,A5,Cleaned_Data!$I$2:$I$315) -> 818510.19 | C5: =SUMIF(Cleaned_Data!$D$2:$D$315,A5,Cleaned_Data!$H$2:$H$315) -> 222
A6: Desk Fan | B6: =SUMIF(Cleaned_Data!$D$2:$D$315,A6,Cleaned_Data!$I$2:$I$315) -> 671777.13 | C6: =SUMIF(Cleaned_Data!$D$2:$D$315,A6,Cleaned_Data!$H$2:$H$315) -> 197
A7: Standing Desk | B7: =SUMIF(Cleaned_Data!$D$2:$D$315,A7,Cleaned_Data!$I$2:$I$315) -> 510827.62 | C7: =SUMIF(Cleaned_Data!$D$2:$D$315,A7,Cleaned_Data!$H$2:$H$315) -> 70
A8: Electric Kettle | B8: =SUMIF(Cleaned_Data!$D$2:$D$315,A8,Cleaned_Data!$I$2:$I$315) -> 416449.13 | C8: =SUMIF(Cleaned_Data!$D$2:$D$315,A8,Cleaned_Data!$H$2:$H$315) -> 135
A9: USB-C Hub | B9: =SUMIF(Cleaned_Data!$D$2:$D$315,A9,Cleaned_Data!$I$2:$I$315) -> 382064.64 | C9: =SUMIF(Cleaned_Data!$D$2:$D$315,A9,Cleaned_Data!$H$2:$H$315) -> 128
A10: Webcam HD | B10: =SUMIF(Cleaned_Data!$D$2:$D$315,A10,Cleaned_Data!$I$2:$I$315) -> 351983.62 | C10: =SUMIF(Cleaned_Data!$D$2:$D$315,A10,Cleaned_Data!$H$2:$H$315) -> 124
A11: Bluetooth Speaker | B11: =SUMIF(Cleaned_Data!$D$2:$D$315,A11,Cleaned_Data!$I$2:$I$315) -> 258554.67 | C11: =SUMIF(Cleaned_Data!$D$2:$D$315,A11,Cleaned_Data!$H$2:$H$315) -> 93
A12: Laptop Stand | B12: =SUMIF(Cleaned_Data!$D$2:$D$315,A12,Cleaned_Data!$I$2:$I$315) -> 254113.86 | C12: =SUMIF(Cleaned_Data!$D$2:$D$315,A12,Cleaned_Data!$H$2:$H$315) -> 109
A13: Wireless Mouse | B13: =SUMIF(Cleaned_Data!$D$2:$D$315,A13,Cleaned_Data!$I$2:$I$315) -> 194057.81 | C13: =SUMIF(Cleaned_Data!$D$2:$D$315,A13,Cleaned_Data!$H$2:$H$315) -> 61
... A17: Notebook Pack | B17: =SUMIF(Cleaned_Data!$D$2:$D$315,A17,Cleaned_Data!$I$2:$I$315) -> 42874.53 | C17: =SUMIF(Cleaned_Data!$D$2:$D$315,A17,Cleaned_Data!$H$2:$H$315) -> 136

Sheet Monthly_Trend
A1: Month | B1: Total Sales | C1: Total Profit
A2: 2024-01 | B2: =SUMPRODUCT((Cleaned_Data!$B$2:$B$315>=DATE(2024,1,1))*(Cleaned_Data!$B$2:$B$315<EDATE(DATE(2024,1,1),1))*Cleaned_Data!$I$2:$I$315) -> 521489.48 | C2: =SUMPRODUCT((Cleaned_Data!$B$2:$B$315>=DATE(2024,1,1))*(Cleaned_Data!$B$2:$B$315<EDATE(DATE(2024,1,1),1))*Cleaned_Data!$G$2:$G$315) -> 83460.75
A3: 2024-02 | B3: =SUMPRODUCT((Cleaned_Data!$B$2:$B$315>=DATE(2024,2,1))*(Cleaned_Data!$B$2:$B$315<EDATE(DATE(2024,2,1),1))*Cleaned_Data!$I$2:$I$315) -> 666935.03 | C3: =SUMPRODUCT((Cleaned_Data!$B$2:$B$315>=DATE(2024,2,1))*(Cleaned_Data!$B$2:$B$315<EDATE(DATE(2024,2,1),1))*Cleaned_Data!$G$2:$G$315) -> 107896.38
A4: 2024-03 | B4: =SUMPRODUCT((Cleaned_Data!$B$2:$B$315>=DATE(2024,3,1))*(Cleaned_Data!$B$2:$B$315<EDATE(DATE(2024,3,1),1))*Cleaned_Data!$I$2:$I$315) -> 818423.81 | C4: =SUMPRODUCT((Cleaned_Data!$B$2:$B$315>=DATE(2024,3,1))*(Cleaned_Data!$B$2:$B$315<EDATE(DATE(2024,3,1),1))*Cleaned_Data!$G$2:$G$315) -> 140532.23
A5: 2024-04 | B5: =SUMPRODUCT((Cleaned_Data!$B$2:$B$315>=DATE(2024,4,1))*(Cleaned_Data!$B$2:$B$315<EDATE(DATE(2024,4,1),1))*Cleaned_Data!$I$2:$I$315) -> 557807.41 | C5: =SUMPRODUCT((Cleaned_Data!$B$2:$B$315>=DATE(2024,4,1))*(Cleaned_Data!$B$2:$B$315<EDATE(DATE(2024,4,1),1))*Cleaned_Data!$G$2:$G$315) -> 86523.54
A6: 2024-05 | B6: =SUMPRODUCT((Cleaned_Data!$B$2:$B$315>=DATE(2024,5,1))*(Cleaned_Data!$B$2:$B$315<EDATE(DATE(2024,5,1),1))*Cleaned_Data!$I$2:$I$315) -> 545263.57 | C6: =SUMPRODUCT((Cleaned_Data!$B$2:$B$315>=DATE(2024,5,1))*(Cleaned_Data!$B$2:$B$315<EDATE(DATE(2024,5,1),1))*Cleaned_Data!$G$2:$G$315) -> 93486.33
A7: 2024-06 | B7: =SUMPRODUCT((Cleaned_Data!$B$2:$B$315>=DATE(2024,6,1))*(Cleaned_Data!$B$2:$B$315<EDATE(DATE(2024,6,1),1))*Cleaned_Data!$I$2:$I$315) -> 474574.1 | C7: =SUMPRODUCT((Cleaned_Data!$B$2:$B$315>=DATE(2024,6,1))*(Cleaned_Data!$B$2:$B$315<EDATE(DATE(2024,6,1),1))*Cleaned_Data!$G$2:$G$315) -> 85900.74
A8: 2024-07 | B8: =SUMPRODUCT((Cleaned_Data!$B$2:$B$315>=DATE(2024,7,1))*(Cleaned_Data!$B$2:$B$315<EDATE(DATE(2024,7,1),1))*Cleaned_Data!$I$2:$I$315) -> 780536.15 | C8: =SUMPRODUCT((Cleaned_Data!$B$2:$B$315>=DATE(2024,7,1))*(Cleaned_Data!$B$2:$B$315<EDATE(DATE(2024,7,1),1))*Cleaned_Data!$G$2:$G$315) -> 119042.5
A9: 2024-08 | B9: =SUMPRODUCT((Cleaned_Data!$B$2:$B$315>=DATE(2024,8,1))*(Cleaned_Data!$B$2:$B$315<EDATE(DATE(2024,8,1),1))*Cleaned_Data!$I$2:$I$315) -> 642044.75 | C9: =SUMPRODUCT((Cleaned_Data!$B$2:$B$315>=DATE(2024,8,1))*(Cleaned_Data!$B$2:$B$315<EDATE(DATE(2024,8,1),1))*Cleaned_Data!$G$2:$G$315) -> 107603.91
A10: 2024-09 | B10: =SUMPRODUCT((Cleaned_Data!$B$2:$B$315>=DATE(2024,9,1))*(Cleaned_Data!$B$2:$B$315<EDATE(DATE(2024,9,1),1))*Cleaned_Data!$I$2:$I$315) -> 392852.04 | C10: =SUMPRODUCT((Cleaned_Data!$B$2:$B$315>=DATE(2024,9,1))*(Cleaned_Data!$B$2:$B$315<EDATE(DATE(2024,9,1),1))*Cleaned_Data!$G$2:$G$315) -> 69376.88
A11: 2024-10 | B11: =SUMPRODUCT((Cleaned_Data!$B$2:$B$315>=DATE(2024,10,1))*(Cleaned_Data!$B$2:$B$315<EDATE(DATE(2024,10,1),1))*Cleaned_Data!$I$2:$I$315) -> 350281.26 | C11: =SUMPRODUCT((Cleaned_Data!$B$2:$B$315>=DATE(2024,10,1))*(Cleaned_Data!$B$2:$B$315<EDATE(DATE(2024,10,1),1))*Cleaned_Data!$G$2:$G$315) -> 58806.85
A12: 2024-11 | B12: =SUMPRODUCT((Cleaned_Data!$B$2:$B$315>=DATE(2024,11,1))*(Cleaned_Data!$B$2:$B$315<EDATE(DATE(2024,11,1),1))*Cleaned_Data!$I$2:$I$315) -> 493935.05 | C12: =SUMPRODUCT((Cleaned_Data!$B$2:$B$315>=DATE(2024,11,1))*(Cleaned_Data!$B$2:$B$315<EDATE(DATE(2024,11,1),1))*Cleaned_Data!$G$2:$G$315) -> 86179.15
A13: 2024-12 | B13: =SUMPRODUCT((Cleaned_Data!$B$2:$B$315>=DATE(2024,12,1))*(Cleaned_Data!$B$2:$B$315<EDATE(DATE(2024,12,1),1))*Cleaned_Data!$I$2:$I$315) -> 604824.01 | C13: =SUMPRODUCT((Cleaned_Data!$B$2:$B$315>=DATE(2024,12,1))*(Cleaned_Data!$B$2:$B$315<EDATE(DATE(2024,12,1),1))*Cleaned_Data!$G$2:$G$315) -> 103192.39
